[
  {
    "id": "elon-musk-of-tweets-january-23-january-30-300-319-serper-2",
    "marketId": "elon-musk-of-tweets-january-23-january-30-300-319",
    "title": "90 tweets over the last few days The graph shows steady ...",
    "source": "x.com",
    "publishedAt": "2026-01-29T19:35:42.562Z",
    "summary": "Elon Musk # tweets January 23 - January 30, 2026? The data shows a clear trajectory of tweet accumulation, with a current line of 269 posts in six days.",
    "url": "https://x.com/PrekrasnaZasmin/status/2016785386169675975",
    "sentiment": "neutral",
    "impactScore": 5,
    "sourceType": "news"
  },
  {
    "id": "elon-musk-of-tweets-january-23-january-30-300-319-serper-9",
    "marketId": "elon-musk-of-tweets-january-23-january-30-300-319",
    "title": "@failstober on Polymarket - t.co / X",
    "source": "t.co",
    "publishedAt": "2026-01-29T17:35:42.562Z",
    "summary": "Will Elon Musk post 340-359 tweets from January 23 to January 30, 2026? Yes. 4,679.3 shares at 3¢. $1,525.46$1,381.52 (959.85%).",
    "url": "https://t.co/mEairQnUhg",
    "sentiment": "bullish",
    "impactScore": 7,
    "sourceType": "news"
  },
  {
    "id": "elon-musk-of-tweets-january-23-january-30-300-319-serper-3",
    "marketId": "elon-musk-of-tweets-january-23-january-30-300-319",
    "title": "Elon Musk's social media platform X, has introduced a new ...",
    "source": "instagram.com",
    "publishedAt": "2026-01-29T10:50:02.870Z",
    "summary": "The feature came to light on January 28, 2026, when the anonymous X account @DogeDesigner, frequently used as a proxy for unveiling platform updates, posted ...",
    "url": "https://www.instagram.com/p/DUFy12-jZBw/",
    "sentiment": "neutral",
    "impactScore": 5,
    "sourceType": "news"
  },
  {
    "id": "elon-musk-of-tweets-january-23-january-30-300-319-serper-7",
    "marketId": "elon-musk-of-tweets-january-23-january-30-300-319",
    "title": "\"#2026\" - Results on X | Live Posts & Updates",
    "source": "x.com",
    "publishedAt": "2026-01-29T08:35:42.562Z",
    "summary": "Elon Musk # tweets January 23 - January 30, 2026? The data shows a clear trajectory of tweet accumulation, with a current line of 269 posts in six ...",
    "url": "https://x.com/hashtag/2026%E3%83%AF%E3%82%B7%E3%81%95%E3%82%93%E5%80%B6%E6%A5%BD%E9%83%A8?src=hashtag_click",
    "sentiment": "neutral",
    "impactScore": 5,
    "sourceType": "news"
  },
  {
    "id": "elon-musk-of-tweets-january-23-january-30-300-319-serper-4",
    "marketId": "elon-musk-of-tweets-january-23-january-30-300-319",
    "title": "@guy5050 on Polymarket",
    "source": "polymarket.com",
    "publishedAt": "2026-01-29T07:35:42.562Z",
    "summary": "Will Elon Musk post 340-359 tweets from January 23 to January 30, 2026? Yes. 1,000.2 shares at 15¢. $184.03$34.23 (22.85%).",
    "url": "https://polymarket.com/profile/0x48ce40bdeb5d8c499471bf09500441ea63290095",
    "sentiment": "neutral",
    "impactScore": 5,
    "sourceType": "news"
  },
  {
    "id": "elon-musk-of-tweets-january-23-january-30-300-319-serper-10",
    "marketId": "elon-musk-of-tweets-january-23-january-30-300-319",
    "title": "Elon Musk # tweets 2026年1月23日至1月30日？",
    "source": "polymarket.com",
    "publishedAt": "2026-01-29T04:35:42.562Z",
    "summary": "This market will resolve according to the number of times Elon Musk (@elonmusk), posts on X from January 23 12:00 PM ET to January 30, 2026 12:00 PM ET.",
    "url": "https://polymarket.com/zh/event/elon-musk-of-tweets-january-23-january-30",
    "sentiment": "neutral",
    "impactScore": 5,
    "sourceType": "news"
  },
  {
    "id": "elon-musk-of-tweets-january-23-january-30-300-319-serper-8",
    "marketId": "elon-musk-of-tweets-january-23-january-30-300-319",
    "title": "Elon Musk # tweets January 29 - January 31, 2026?",
    "source": "mlq.ai",
    "publishedAt": "2026-01-29T00:50:02.870Z",
    "summary": "Elon Musk # tweets January 29 - January 31, 2026? This market will resolve according to the number of times Elon Musk (@elonmusk), posts on X from January ...",
    "url": "https://mlq.ai/prediction/market/elon-musk-of-tweets-january-29-january-31/",
    "sentiment": "neutral",
    "impactScore": 5,
    "sourceType": "news"
  },
  {
    "id": "elon-musk-of-tweets-january-23-january-30-300-319-serper-8",
    "marketId": "elon-musk-of-tweets-january-23-january-30-300-319",
    "title": "Elon Musk # tweets January 20 - January 27, 2026?",
    "source": "polymarket.com",
    "publishedAt": "2026-01-27T19:35:42.562Z",
    "summary": "This market will resolve according to the number of times Elon Musk (@elonmusk), posts on X from January 20 12:00 PM ET to January 27, 2026 12:00 PM ET.",
    "url": "https://polymarket.com/event/elon-musk-of-tweets-january-20-january-27",
    "sentiment": "neutral",
    "impactScore": 5,
    "sourceType": "news"
  },
  {
    "id": "elon-musk-of-tweets-january-23-january-30-300-319-serper-1",
    "marketId": "elon-musk-of-tweets-january-23-january-30-300-319",
    "title": "Elon Musk # tweets January 30 - February 6, 2026?",
    "source": "polymarket.com",
    "publishedAt": "2026-01-27T13:50:02.870Z",
    "summary": "View real-time odds on \"Elon Musk # tweets January 30 - February 6, 2026?\" as of January 29, 2026, and trade on The World's Largest Prediction Market™",
    "url": "https://polymarket.com/event/elon-musk-of-tweets-january-30-february-6",
    "sentiment": "neutral",
    "impactScore": 5,
    "sourceType": "news"
  },
  {
    "id": "elon-musk-of-tweets-january-23-january-30-300-319-serper-9",
    "marketId": "elon-musk-of-tweets-january-23-january-30-300-319",
    "title": "Musk & Altman high-like tweets",
    "source": "scouts.yutori.com",
    "publishedAt": "2026-01-27T13:50:02.870Z",
    "summary": "Two Elon Musk tweets on January 21, 2026 surpassed the 100k-like threshold; no Sam Altman tweets reached 10k+ likes in this window. \"AI is a supersonic tsunami\" ...",
    "url": "https://scouts.yutori.com/df1abdc1-d64c-44b2-a972-2d5e36c3de53",
    "sentiment": "neutral",
    "impactScore": 5,
    "sourceType": "news"
  },
  {
    "id": "elon-musk-of-tweets-january-23-january-30-300-319-serper-6",
    "marketId": "elon-musk-of-tweets-january-23-january-30-300-319",
    "title": "Elon Musk # tweets January 23 - January 30, 2026? ...",
    "source": "polymarket.com",
    "publishedAt": "2026-01-26T19:35:42.562Z",
    "summary": "View real-time odds on \"Elon Musk # tweets January 23 - January 30, 2026?\" as of January 27, 2026, and trade on The World's Largest Prediction Market™",
    "url": "https://polymarket.com/event/elon-musk-of-tweets-january-23-january-30/elon-musk-of-tweets-january-23-january-30-420-439",
    "sentiment": "neutral",
    "impactScore": 5,
    "sourceType": "news"
  },
  {
    "id": "elon-musk-of-tweets-january-23-january-30-300-319-serper-2",
    "marketId": "elon-musk-of-tweets-january-23-january-30-300-319",
    "title": "Elon Musk # tweets January 29 - January 31, 2026?",
    "source": "polymarket.com",
    "publishedAt": "2026-01-26T13:50:02.870Z",
    "summary": "View real-time odds on \"Elon Musk # tweets January 29 - January 31, 2026?\" as of January 29, 2026, and trade on The World's Largest Prediction Market™",
    "url": "https://polymarket.com/event/elon-musk-of-tweets-january-29-january-31",
    "sentiment": "neutral",
    "impactScore": 5,
    "sourceType": "news"
  },
  {
    "id": "elon-musk-of-tweets-january-23-january-30-300-319-serper-6",
    "marketId": "elon-musk-of-tweets-january-23-january-30-300-319",
    "title": "Why Elon Musk's hiring tweet favors AI-native talent",
    "source": "hrexecutive.com",
    "publishedAt": "2026-01-26T13:50:02.870Z",
    "summary": "Elon Musk posted a job asking for 3 bullet points and candidates used his own AI tool to apply. What does this say about talent acquisition?",
    "url": "https://hrexecutive.com/what-elon-musks-viral-recruiting-tweet-reveals-about-hirings-murky-future/",
    "sentiment": "neutral",
    "impactScore": 5,
    "sourceType": "news"
  },
  {
    "id": "elon-musk-of-tweets-january-23-january-30-300-319-serper-4",
    "marketId": "elon-musk-of-tweets-january-23-january-30-300-319",
    "title": "Elon Musk # tweets January 16 - Prediction Markets",
    "source": "perplexity.ai",
    "publishedAt": "2026-01-24T13:50:02.870Z",
    "summary": "The market has decisively converged on the 460-479 tweet range with 99.95% probability and massive $25M+ volume, indicating Elon is tracking at ...",
    "url": "https://www.perplexity.ai/finance/predictions/160906",
    "sentiment": "bearish",
    "impactScore": 7,
    "sourceType": "news"
  },
  {
    "id": "elon-musk-of-tweets-january-23-january-30-300-319-serper-10",
    "marketId": "elon-musk-of-tweets-january-23-january-30-300-319",
    "title": "50 of the Funniest Tweets from the Week of January 19, 2026",
    "source": "trivia.cracked.com",
    "publishedAt": "2026-01-24T13:50:02.870Z",
    "summary": "Meanwhile, Twitter had a blast this week. The funniest tweets include a steak, AI filmmaking, and hypocritical customers. Advertisement.",
    "url": "https://trivia.cracked.com/image-pictofact-18974-50-of-the-funniest-tweets-from-the-week-of-january-19-2026",
    "sentiment": "neutral",
    "impactScore": 5,
    "sourceType": "news"
  },
  {
    "id": "elon-musk-of-tweets-january-23-january-30-300-319-serper-1",
    "marketId": "elon-musk-of-tweets-january-23-january-30-300-319",
    "title": "Elon Musk # tweets January 23 - January 30, 2026? ...",
    "source": "polymarket.com",
    "publishedAt": "2026-01-23T19:35:42.562Z",
    "summary": "View real-time odds on \"Elon Musk # tweets January 23 - January 30, 2026?\" as of January 29, 2026, and trade on The World's Largest Prediction Market™",
    "url": "https://polymarket.com/event/elon-musk-of-tweets-january-23-january-30/elon-musk-of-tweets-january-23-january-30-340-359",
    "sentiment": "neutral",
    "impactScore": 5,
    "sourceType": "news"
  },
  {
    "id": "elon-musk-of-tweets-january-23-january-30-300-319-serper-3",
    "marketId": "elon-musk-of-tweets-january-23-january-30-300-319",
    "title": "Elon Musk # tweets January 23 - January 30, 2026? ...",
    "source": "polymarket.com",
    "publishedAt": "2026-01-23T19:35:42.562Z",
    "summary": "View real-time odds on \"Elon Musk # tweets January 23 - January 30, 2026?\" as of January 28, 2026, and trade on The World's Largest Prediction Market™",
    "url": "https://polymarket.com/event/elon-musk-of-tweets-january-23-january-30/elon-musk-of-tweets-january-23-january-30-320-339",
    "sentiment": "neutral",
    "impactScore": 5,
    "sourceType": "news"
  },
  {
    "id": "elon-musk-of-tweets-january-23-january-30-300-319-serper-5",
    "marketId": "elon-musk-of-tweets-january-23-january-30-300-319",
    "title": "Elon Musk # tweets January 27 - February 3, 2026? - t.co / X",
    "source": "t.co",
    "publishedAt": "2026-01-23T19:35:42.562Z",
    "summary": "View real-time odds on \"Elon Musk # tweets January 27 - February 3, 2026?\" as of January 29, 2026, and trade on The World's Largest Prediction Market™",
    "url": "https://t.co/1eIKxt4U3E",
    "sentiment": "neutral",
    "impactScore": 5,
    "sourceType": "news"
  },
  {
    "id": "elon-musk-of-tweets-january-23-january-30-300-319-serper-7",
    "marketId": "elon-musk-of-tweets-january-23-january-30-300-319",
    "title": "X Suddenly Has a Lot of 'Article' Posts. It's Offering $1 Million.",
    "source": "businessinsider.com",
    "publishedAt": "2026-01-23T13:50:02.870Z",
    "summary": "Elon Musk's X is now offering a $1 million prize to whoever has the most viral article in the next week or so. As you might imagine, this has created a glut of ...",
    "url": "https://www.businessinsider.com/x-elon-musk-twitter-articles-feature-content-million-dollars-2026-1",
    "sentiment": "neutral",
    "impactScore": 5,
    "sourceType": "news"
  }
]