[
  {
    "id": "elon-musk-of-tweets-january-20-january-27-520-539-serper-1",
    "marketId": "elon-musk-of-tweets-january-20-january-27-520-539",
    "title": "Elon Musk # tweets January 20 - January 27, 2026? ...",
    "source": "polymarket.com",
    "publishedAt": "2026-01-20T17:02:37.126Z",
    "summary": "This market will resolve according to the number of times Elon Musk (@elonmusk), posts on X from January 20 12:00 PM ET to January 27, 2026 12:00 PM ET.",
    "url": "https://polymarket.com/event/elon-musk-of-tweets-january-20-january-27/elon-musk-of-tweets-january-20-january-27-340-359",
    "sentiment": "neutral",
    "impactScore": 5,
    "sourceType": "news"
  },
  {
    "id": "elon-musk-of-tweets-january-20-january-27-520-539-serper-2",
    "marketId": "elon-musk-of-tweets-january-20-january-27-520-539",
    "title": "Elon Musk # tweets January 20 - January 27, 2026?",
    "source": "polymarket.com",
    "publishedAt": "2026-01-20T17:02:37.126Z",
    "summary": "View real-time odds on \"Elon Musk # tweets January 20 - January 27, 2026?\" as of January 20, 2026, and trade on The World's Largest Prediction Market™",
    "url": "https://polymarket.com/event/elon-musk-of-tweets-january-20-january-27/elon-musk-of-tweets-january-20-january-27-540-559",
    "sentiment": "neutral",
    "impactScore": 5,
    "sourceType": "news"
  },
  {
    "id": "elon-musk-of-tweets-january-20-january-27-520-539-serper-3",
    "marketId": "elon-musk-of-tweets-january-20-january-27-520-539",
    "title": "Elon Musk # tweets January 30 - February 6, 2026?",
    "source": "polymarket.com",
    "publishedAt": "2026-01-27T06:02:37.126Z",
    "summary": "View real-time odds on \"Elon Musk # tweets January 30 - February 6, 2026?\" as of January 26, 2026, and trade on The World's Largest Prediction Market™",
    "url": "https://polymarket.com/event/elon-musk-of-tweets-january-30-february-6/elon-musk-of-tweets-january-30-february-6-520-539",
    "sentiment": "neutral",
    "impactScore": 5,
    "sourceType": "news"
  },
  {
    "id": "elon-musk-of-tweets-january-20-january-27-520-539-serper-4",
    "marketId": "elon-musk-of-tweets-january-20-january-27-520-539",
    "title": "Prediction Market Volume Tracker",
    "source": "defirate.com",
    "publishedAt": "2026-01-27T04:02:37.126Z",
    "summary": "Elon Musk # tweets January 20 - January 27, 2026? Polymarket. Tech Closing Soon. 400–419 35%. 380–399 27%. View All 20 Options. 420–439 16%. 360–379 10%. 440 ...",
    "url": "https://defirate.com/prediction-markets/",
    "sentiment": "neutral",
    "impactScore": 5,
    "sourceType": "news"
  },
  {
    "id": "elon-musk-of-tweets-january-20-january-27-520-539-serper-5",
    "marketId": "elon-musk-of-tweets-january-20-january-27-520-539",
    "title": "Elon Musk # tweets January 13 - January 20, 2026?",
    "source": "polymarket.com",
    "publishedAt": "2026-01-27T11:02:37.126Z",
    "summary": "Elon Musk # tweets January 13 - January 20, 2026? (Resolved): View the final results and historical odds on The World's Largest Prediction Market™",
    "url": "https://polymarket.com/event/elon-musk-of-tweets-january-13-january-20",
    "sentiment": "neutral",
    "impactScore": 5,
    "sourceType": "news"
  },
  {
    "id": "elon-musk-of-tweets-january-20-january-27-520-539-serper-6",
    "marketId": "elon-musk-of-tweets-january-20-january-27-520-539",
    "title": "DPool (@0xDPool) / Posts / X",
    "source": "x.com",
    "publishedAt": "2026-01-27T16:05:23.828Z",
    "summary": "Don't miss out on the opportunity to earn 100% to 243% on Elon Musk's posts. A new market based on Elon Musk's posts is now available: January 23 - January 30",
    "url": "https://x.com/0xDPool",
    "sentiment": "neutral",
    "impactScore": 5,
    "sourceType": "news"
  },
  {
    "id": "elon-musk-of-tweets-january-20-january-27-520-539-serper-7",
    "marketId": "elon-musk-of-tweets-january-20-january-27-520-539",
    "title": "Elon Musk # tweets January 27 - February 3, 2026?",
    "source": "polymarket.com",
    "publishedAt": "2026-01-24T17:02:37.126Z",
    "summary": "This market will resolve according to the number of times Elon Musk (@elonmusk), posts on X from January 27 12:00 PM ET to February 3, 2026 12:00 PM ET.",
    "url": "https://polymarket.com/event/elon-musk-of-tweets-january-27-february-3/elon-musk-of-tweets-january-27-february-3-620-639",
    "sentiment": "neutral",
    "impactScore": 5,
    "sourceType": "news"
  },
  {
    "id": "elon-musk-of-tweets-january-20-january-27-520-539-serper-8",
    "marketId": "elon-musk-of-tweets-january-20-january-27-520-539",
    "title": "Elon Musk # tweets January 13 - January 20, 2026? ...",
    "source": "polymarket.com",
    "publishedAt": "2026-01-20T17:02:37.126Z",
    "summary": "Elon Musk # tweets January 13 - January 20, 2026? ; 520-539. $1,427,395 Vol. ; 540-559. $1,236,193 Vol. ; 560-579. $1,442,274 Vol. ; 580-599. $1,189,127 Vol. ; 600- ...",
    "url": "https://polymarket.com/event/elon-musk-of-tweets-january-13-january-20/elon-musk-of-tweets-january-13-january-20-580-599",
    "sentiment": "neutral",
    "impactScore": 5,
    "sourceType": "news"
  },
  {
    "id": "elon-musk-of-tweets-january-20-january-27-520-539-serper-9",
    "marketId": "elon-musk-of-tweets-january-20-january-27-520-539",
    "title": "Elon Musk # tweets January 30 - February 6, 2026?",
    "source": "polymarket.com",
    "publishedAt": "2026-01-27T06:02:37.126Z",
    "summary": "View real-time odds on \"Elon Musk # tweets January 30 - February 6, 2026?\" as of January 27, 2026, and trade on The World's Largest Prediction Market™",
    "url": "https://polymarket.com/event/elon-musk-of-tweets-january-30-february-6/elon-musk-of-tweets-january-30-february-6-40-59",
    "sentiment": "neutral",
    "impactScore": 5,
    "sourceType": "news"
  },
  {
    "id": "elon-musk-of-tweets-january-20-january-27-520-539-serper-10",
    "marketId": "elon-musk-of-tweets-january-20-january-27-520-539",
    "title": "\"#520\" - Results on X | Live Posts & Updates",
    "source": "x.com",
    "publishedAt": "2026-01-24T17:02:37.126Z",
    "summary": "- January 20: 520-539 tweets - January 23: 460-479 tweets - Market ... How many tweets do you think Elon Musk will make by January 27? mahera's ...",
    "url": "https://x.com/hashtag/520%E3%81%AF%E3%81%B4%E3%81%94%E3%82%86%E3%81%8A%E5%93%81%E6%9B%B8%E3%81%8D?src=hashtag_click",
    "sentiment": "neutral",
    "impactScore": 5,
    "sourceType": "news"
  }
]