[
  {
    "id": "nba-den-nyk-2026-02-04-serper-5",
    "marketId": "nba-den-nyk-2026-02-04",
    "title": "Denver Nuggets vs New York Knicks Odds - Wednesday February 4 2026",
    "source": "Odds Shark",
    "publishedAt": "2026-02-04T19:31:41.652Z",
    "summary": "Denver Nuggets vs New York Knicks Odds - Wednesday February 4 2026. Live betting odds and lines, betting trends, against the spread and...",
    "url": "https://www.oddsshark.com/nba/denver-new-york-odds-february-4-2026-2460624",
    "imageUrl": "https://encrypted-tbn0.gstatic.com/images?q=tbn:ANd9GcRdxl3l_l2LvbJ7Ykehm445irj5muPXhVOcy6le5I03hI99jVqPZ1hLaqU&usqp=CAI&s",
    "sentiment": "neutral",
    "impactScore": 5,
    "sourceType": "news"
  },
  {
    "id": "nba-den-nyk-2026-02-04-serper-7",
    "marketId": "nba-den-nyk-2026-02-04",
    "title": "Fanatics Sportsbook Promo Code GOALBONUS: Get $1000 in FanCash for Nuggets vs Knicks, NHL & EFL Cup",
    "source": "Goal.com",
    "publishedAt": "2026-02-04T18:39:41.652Z",
    "summary": "Fanatics Sportsbook Promo Code GOALBONUS offers $1000 in FanCash for wagers on Nuggets vs Knicks, plus EFL Cup and NHL action (2/4).",
    "url": "https://www.goal.com/en-us/betting/fanatics-sportsbook-promo-code-goalbonus-get-1000-fancash-nuggets-vs-knicks-nhl-efl-cup-2-4/blt120e4de2f0923e6c",
    "imageUrl": "https://encrypted-tbn0.gstatic.com/images?q=tbn:ANd9GcS9krpwT9zV1ajxdN9vDR-UsPnC3kCeulGQ7bAI38Njz3PORpAK9FIs09Q&usqp=CAI&s",
    "sentiment": "neutral",
    "impactScore": 5,
    "sourceType": "news"
  },
  {
    "id": "nba-den-nyk-2026-02-04-serper-3",
    "marketId": "nba-den-nyk-2026-02-04",
    "title": "Nuggets vs. Knicks Prediction, Odds and Best NBA Prop Bets for Wednesday, Feb. 4",
    "source": "Sports Illustrated",
    "publishedAt": "2026-02-04T17:39:41.652Z",
    "summary": "",
    "url": "https://www.si.com/betting/nuggets-vs-knicks-prediction-odds-and-best-nba-prop-bets-for-wednesday-feb-4",
    "imageUrl": "https://encrypted-tbn0.gstatic.com/images?q=tbn:ANd9GcRcBf5cgXq9xPb7vt_SOIfuc_uZUV5bE7_xcOgHjtHK06XrQzNWc1U1ZlY&usqp=CAI&s",
    "sentiment": "neutral",
    "impactScore": 5,
    "sourceType": "news"
  },
  {
    "id": "nba-den-nyk-2026-02-04-serper-2",
    "marketId": "nba-den-nyk-2026-02-04",
    "title": "NBA picks: Nuggets vs. Knicks same-game parlay for Wednesday, Feb. 4 includes Jalen Brunson",
    "source": "CBS Sports",
    "publishedAt": "2026-02-04T16:39:41.652Z",
    "summary": "",
    "url": "https://www.cbssports.com/nba/news/nba-picks-nuggets-vs-knicks-same-game-parlay-for-wednesday-feb-4-includes-jalen-brunson/",
    "imageUrl": "https://encrypted-tbn0.gstatic.com/images?q=tbn:ANd9GcRqocTYuayzY9VB-rHDC6SXpLMBBkNZJP0nJuP6Lr6CQjmUGQcPDr1jkVU&usqp=CAI&s",
    "sentiment": "neutral",
    "impactScore": 5,
    "sourceType": "news"
  },
  {
    "id": "nba-den-nyk-2026-02-04-serper-9",
    "marketId": "nba-den-nyk-2026-02-04",
    "title": "Underdog Promo Code WTOP: Get $75 Bonus for Nuggets-Knicks, NBA, SB LX",
    "source": "WTOP",
    "publishedAt": "2026-02-04T16:39:41.652Z",
    "summary": "The Underdog promo code WTOP will score a $75 bonus for fantasy entries on Nuggets-Knicks, NBA and SB LX Picks.",
    "url": "https://wtop.com/sports/2026/02/underdog-promo-code-wtop-get-75-bonus-for-nuggets-knicks-nba-sb-lx/",
    "imageUrl": "https://encrypted-tbn0.gstatic.com/images?q=tbn:ANd9GcTh27yDHhwdXZqgI4LKWnt57J2NnOfV11dWcNLEASZoHFAiYk_GSOOvAfY&usqp=CAI&s",
    "sentiment": "neutral",
    "impactScore": 5,
    "sourceType": "news"
  },
  {
    "id": "nba-den-nyk-2026-02-04-serper-4",
    "marketId": "nba-den-nyk-2026-02-04",
    "title": "Nuggets vs. Knicks predictions: Odds, recent stats, trends and best bets for February 4",
    "source": "NBC Sports",
    "publishedAt": "2026-02-04T15:39:41.652Z",
    "summary": "Riding a seven-game winning streak, Jalen Brunson and the New York Knicks (32-18) host Nikola Jokic and the Denver Nuggets (33-18) tonight...",
    "url": "https://www.nbcsports.com/betting/nba/news/nuggets-vs-knicks-predictions-odds-recent-stats-trends-and-best-bets-for-february-4",
    "imageUrl": "https://encrypted-tbn0.gstatic.com/images?q=tbn:ANd9GcTstDLvtDPBdUN8zSdFnxDlGdRREFCiTLnitbgZzUp1EGjWaENP_YbTsj0&usqp=CAI&s",
    "sentiment": "neutral",
    "impactScore": 5,
    "sourceType": "news"
  },
  {
    "id": "nba-den-nyk-2026-02-04-serper-0",
    "marketId": "nba-den-nyk-2026-02-04",
    "title": "Denver Nuggets vs New York Knicks Prediction, Pick, Odds -- 2/4",
    "source": "Action Network",
    "publishedAt": "2026-02-04T14:39:41.652Z",
    "summary": "",
    "url": "https://www.actionnetwork.com/nba/denver-nuggets-vs-new-york-knicks-prediction-pick-odds-wednesday-february-4",
    "imageUrl": "https://encrypted-tbn0.gstatic.com/images?q=tbn:ANd9GcSughxbxSa7JE1GwX4JnYqNnduyykXPZsh-6dOhIrMJzWnCwAK0T7IA3FM&usqp=CAI&s",
    "sentiment": "neutral",
    "impactScore": 5,
    "sourceType": "news"
  },
  {
    "id": "nba-den-nyk-2026-02-04-serper-8",
    "marketId": "nba-den-nyk-2026-02-04",
    "title": "New York Knicks vs. Denver Nuggets odds, tips and betting trends | February 4, 2026",
    "source": "Sportsbook Wire",
    "publishedAt": "2026-02-04T09:39:41.652Z",
    "summary": "Preview the New York Knicks' NBA matchup with Denver, including betting odds, tips, trends, and game information.",
    "url": "https://sportsbookwire.usatoday.com/story/sports/sports-betting/2026/02/04/nba-new-york-knicks-vs-denver-nuggets-betting-odds-tips-trends-2-4-2026/88504968007/",
    "imageUrl": "https://encrypted-tbn0.gstatic.com/images?q=tbn:ANd9GcRDUmM5MipDhg52YjWxiSwEjfGedK4El7M1uE7clr-FXJMDFM0ubfFBIJY&usqp=CAI&s",
    "sentiment": "neutral",
    "impactScore": 5,
    "sourceType": "news"
  },
  {
    "id": "nba-den-nyk-2026-02-04-serper-1",
    "marketId": "nba-den-nyk-2026-02-04",
    "title": "Denver Nuggets vs New York Knicks Prediction, 2/4/2026 Preview and Pick",
    "source": "Doc's Sports",
    "publishedAt": "2026-02-03T22:39:41.652Z",
    "summary": "",
    "url": "https://www.docsports.com/free-picks/nba/2026/denver-nuggets-vs-new-york-knicks-prediction-2-4-2026-preview-and-pick.html",
    "imageUrl": "https://encrypted-tbn0.gstatic.com/images?q=tbn:ANd9GcS9zMSwBVWlp-kL7onBWNNg7NCSoVUT2GX4j8oIF66lbp31Cadz7DfhLn0&usqp=CAI&s",
    "sentiment": "neutral",
    "impactScore": 5,
    "sourceType": "news"
  },
  {
    "id": "nba-den-nyk-2026-02-04-serper-6",
    "marketId": "nba-den-nyk-2026-02-04",
    "title": "NBA Power Rankings: Nikola Jokić’s return lifts Nuggets; Knicks, Hornets, Wolves rise - The Athletic",
    "source": "The New York Times",
    "publishedAt": "2026-02-03T19:39:41.652Z",
    "summary": "LeBron going home? Giannis heading west? We're giving each squad an ideal trade candidate for the short-term future.",
    "url": "https://www.nytimes.com/athletic/7015585/2026/02/02/nba-power-rankings-nuggets-timberwolves-knicks/",
    "imageUrl": "https://encrypted-tbn0.gstatic.com/images?q=tbn:ANd9GcQuNotHaA67cskb2MD0I_VADQAl2m7Nkjp4cvlt3-Hm9e2FEQN5txou-jc&usqp=CAI&s",
    "sentiment": "bullish",
    "impactScore": 7,
    "sourceType": "news"
  }
]