[
  {
    "id": "nhl-bos-tb-2026-02-01-serper-4",
    "marketId": "nhl-bos-tb-2026-02-01",
    "title": "Where to watch Bruins vs. Lightning FREE STREAM today: NHL Stadium Series 2026",
    "source": "Cleveland.com",
    "publishedAt": "2026-02-01T18:30:25.917Z",
    "summary": "",
    "url": "https://www.cleveland.com/tv/2026/02/where-to-watch-bruins-vs-lightning-free-stream-today-nhl-stadium-series.html",
    "imageUrl": "https://encrypted-tbn0.gstatic.com/images?q=tbn:ANd9GcQynijUhY1creDHQmRoqxVtwiWQQ24YLNyL0-g9MU2FjxYYAiwtU_e7HIo&usqp=CAI&s",
    "sentiment": "neutral",
    "impactScore": 5,
    "sourceType": "news"
  },
  {
    "id": "nhl-bos-tb-2026-02-01-serper-6",
    "marketId": "nhl-bos-tb-2026-02-01",
    "title": "Bruins vs. Lightning odds, prediction, spread, time: 2026 NHL Stadium Series picks for February 1 from model",
    "source": "CBS Sports",
    "publishedAt": "2026-02-01T18:30:25.917Z",
    "summary": "",
    "url": "https://www.cbssports.com/nhl/news/bruins-lightning-odds-prediction-spread-time-2026-nhl-stadium-series-picks-february-1/",
    "imageUrl": "https://encrypted-tbn0.gstatic.com/images?q=tbn:ANd9GcQePPrHUgyJAVN2IbT3fHAUbPFPrjj1o04jMfGXNFIEMroJAh2IVePWOF4&usqp=CAI&s",
    "sentiment": "neutral",
    "impactScore": 5,
    "sourceType": "news"
  },
  {
    "id": "nhl-bos-tb-2026-02-01-serper-1",
    "marketId": "nhl-bos-tb-2026-02-01",
    "title": "Lightning vs. Bruins Stadium Series game: Start time, how to watch",
    "source": "USA Today",
    "publishedAt": "2026-02-01T16:30:25.917Z",
    "summary": "",
    "url": "https://www.usatoday.com/story/sports/nhl/2026/02/01/stadium-series-lightning-bruins-how-to-watch-results/88450925007/",
    "imageUrl": "https://encrypted-tbn0.gstatic.com/images?q=tbn:ANd9GcSF9hON8nc04tc9HQNX_-dxJ4NF3g_vmGn58Faz7KxZ7X19lVmALrSV89k&usqp=CAI&s",
    "sentiment": "neutral",
    "impactScore": 5,
    "sourceType": "news"
  },
  {
    "id": "nhl-bos-tb-2026-02-01-serper-2",
    "marketId": "nhl-bos-tb-2026-02-01",
    "title": "Bruins vs Lightning Prediction, Picks & Odds for Tonight’s NHL Game",
    "source": "Covers.com",
    "publishedAt": "2026-02-01T16:30:25.917Z",
    "summary": "",
    "url": "https://www.covers.com/nhl/bruins-vs-lightning-prediction-picks-best-bets-sgp-sunday-2-1-2026",
    "imageUrl": "https://encrypted-tbn0.gstatic.com/images?q=tbn:ANd9GcRilTbnpvOf2DxOOzI3s2Fzu6scF-SY-cbPuQ8tPidbhmHp47mkMmosBPI&usqp=CAI&s",
    "sentiment": "neutral",
    "impactScore": 5,
    "sourceType": "news"
  },
  {
    "id": "nhl-bos-tb-2026-02-01-serper-8",
    "marketId": "nhl-bos-tb-2026-02-01",
    "title": "How To Watch Bruins vs. Lightning Tonight: Channel, Live Stream & Start Time For Stadium Series Game",
    "source": "NESN",
    "publishedAt": "2026-02-01T14:30:25.917Z",
    "summary": "",
    "url": "https://nesn.com/2026/02/how-to-watch-bruins-vs-lightning-channel-stream-start-time/",
    "imageUrl": "https://encrypted-tbn0.gstatic.com/images?q=tbn:ANd9GcRjWl4h7r_OXfW4oXjjI3tKjGr4Squ5s1gvG_8r6h3eKn7yvCpl7R9Yafg&usqp=CAI&s",
    "sentiment": "neutral",
    "impactScore": 5,
    "sourceType": "news"
  },
  {
    "id": "nhl-bos-tb-2026-02-01-serper-3",
    "marketId": "nhl-bos-tb-2026-02-01",
    "title": "NHL Bruins vs Lightning Best Bets, Stadium Series Prediction, Pick, Odds",
    "source": "Action Network",
    "publishedAt": "2026-02-01T05:30:25.917Z",
    "summary": "",
    "url": "https://www.actionnetwork.com/nhl/nhl-bruins-vs-lightning-best-bets-stadium-series-prediction-pick-odds",
    "imageUrl": "https://encrypted-tbn0.gstatic.com/images?q=tbn:ANd9GcSdhV2mU2z8O716Iug19Z9jHYVj2NbXp7SgZXJ63CPvrzyo4L9OP8SAa6Q&usqp=CAI&s",
    "sentiment": "neutral",
    "impactScore": 5,
    "sourceType": "news"
  },
  {
    "id": "nhl-bos-tb-2026-02-01-serper-5",
    "marketId": "nhl-bos-tb-2026-02-01",
    "title": "Boston Bruins vs Tampa Bay Lightning Prediction, 2/1/2026 NHL Picks, Best Bets & Odds",
    "source": "Doc's Sports",
    "publishedAt": "2026-02-01T01:30:25.917Z",
    "summary": "",
    "url": "https://www.docsports.com/free-picks/nhl-hockey/2026/boston-bruins-vs-tampa-bay-lightning-prediction-2-1-2026-nhl-picks-best-bets-odds.html",
    "imageUrl": "https://encrypted-tbn0.gstatic.com/images?q=tbn:ANd9GcTENZYT2U1eJfJh1sUWQ00wS4SAIfdu1Dran20fFs7hZL1OJ7W1GcywRFA&usqp=CAI&s",
    "sentiment": "neutral",
    "impactScore": 5,
    "sourceType": "news"
  },
  {
    "id": "nhl-bos-tb-2026-02-01-serper-0",
    "marketId": "nhl-bos-tb-2026-02-01",
    "title": "Bruins and Lightning excited for colder-than-expected Stadium Series in Tampa",
    "source": "ESPN",
    "publishedAt": "2026-02-01T00:30:25.917Z",
    "summary": "",
    "url": "https://www.espn.com/nhl/story/_/id/47790875/bruins-lightning-colder-expected-2026-stadium-series-tampa",
    "imageUrl": "https://encrypted-tbn0.gstatic.com/images?q=tbn:ANd9GcTw_s8oY4oeZ_PUAnEzqS-6-MDU00ie0MoV1r8T0DHkncaOYXQRog6L3cbysg&usqp=CAI&s",
    "sentiment": "neutral",
    "impactScore": 5,
    "sourceType": "news"
  },
  {
    "id": "nhl-bos-tb-2026-02-01-serper-9",
    "marketId": "nhl-bos-tb-2026-02-01",
    "title": "Bruins expected to be shorthanded for Stadium Series game vs. Lightning",
    "source": "98.5 The Sports Hub",
    "publishedAt": "2026-01-31T19:30:25.917Z",
    "summary": "The Bruins are expected to be without two key players for Sunday's 2026 Stadium Series showdown with the Lightning.",
    "url": "https://985thesportshub.com/2026/01/30/bruins-expected-to-be-shorthanded-for-stadium-series-game-vs-lightning/",
    "imageUrl": "https://encrypted-tbn0.gstatic.com/images?q=tbn:ANd9GcSc8JwOplM8Em9RORece1RPNQiQYVc1BdOHjqW00TUka-yQ_T0E3JuB_I8&usqp=CAI&s",
    "sentiment": "bearish",
    "impactScore": 7,
    "sourceType": "news"
  },
  {
    "id": "nhl-bos-tb-2026-02-01-serper-7",
    "marketId": "nhl-bos-tb-2026-02-01",
    "title": "Bruins look to seize opportunity to gain on Lightning in Stadium Series matchup",
    "source": "NHL.com",
    "publishedAt": "2026-01-30T19:30:25.917Z",
    "summary": "",
    "url": "https://www.nhl.com/news/bruins-seek-to-gain-on-lightning-in-stadium-series-showdown",
    "imageUrl": "https://encrypted-tbn0.gstatic.com/images?q=tbn:ANd9GcSMlf8U09aMk7psGv1dmCyhaiav75rSBQzYuTdfCJQuId8KQ5fr_GkYayM&usqp=CAI&s",
    "sentiment": "bullish",
    "impactScore": 7,
    "sourceType": "news"
  }
]